loramon/__init__.py
loramon/loramon.py
loramon-0.9.7.dist-info/LICENSE
loramon-0.9.7.dist-info/METADATA
loramon-0.9.7.dist-info/WHEEL
loramon-0.9.7.dist-info/entry_points.txt
loramon-0.9.7.dist-info/top_level.txt
loramon-0.9.7.dist-info/RECORD
