Metadata-Version: 2.1
Name: loramon
Version: 0.9.7
Summary: LoRa packet sniffer for RNode hardware
Home-page: https://github.com/markqvist/loramon
Author: Mark Qvist
Author-email: mark@unsigned.io
License: UNKNOWN
Platform: UNKNOWN
Classifier: Programming Language :: Python :: 3
Classifier: License :: OSI Approved :: MIT License
Classifier: Operating System :: OS Independent
Requires-Python: >=3.6
License-File: LICENSE
